playground.py
cjw296_playground-0.1.0.dist-info/WHEEL
cjw296_playground-0.1.0.dist-info/METADATA
cjw296_playground-0.1.0.dist-info/RECORD
